{"text": " french music My daddy wears Pringles What he hate My marvelous dad I'm calling my dad And my mom And you Why the world Hayward And you And youatt detectives And you All of you Don't adopted me Even you Only you All of you", "segments": [{"id": 0, "seek": 0, "start": 0.0, "end": 5.7, "text": " french music", "tokens": [50363, 48718, 2647, 50648], "temperature": 1.0, "avg_logprob": -3.81935543484158, "compression_ratio": 1.0786516853932584, "no_speech_prob": 0.179056778550148}, {"id": 1, "seek": 0, "start": 19.34, "end": 21.42, "text": " My daddy wears Pringles", "tokens": [51330, 2011, 35822, 17326, 1736, 278, 829, 51434], "temperature": 1.0, "avg_logprob": -3.81935543484158, "compression_ratio": 1.0786516853932584, "no_speech_prob": 0.179056778550148}, {"id": 2, "seek": 0, "start": 21.42, "end": 23.0, "text": " What he hate", "tokens": [51434, 1867, 339, 5465, 51513], "temperature": 1.0, "avg_logprob": -3.81935543484158, "compression_ratio": 1.0786516853932584, "no_speech_prob": 0.179056778550148}, {"id": 3, "seek": 0, "start": 23.0, "end": 25.62, "text": " My marvelous dad", "tokens": [51513, 2011, 43937, 9955, 51644], "temperature": 1.0, "avg_logprob": -3.81935543484158, "compression_ratio": 1.0786516853932584, "no_speech_prob": 0.179056778550148}, {"id": 4, "seek": 0, "start": 25.62, "end": 28.28, "text": " I'm calling my dad", "tokens": [51644, 314, 1101, 4585, 616, 9955, 51777], "temperature": 1.0, "avg_logprob": -3.81935543484158, "compression_ratio": 1.0786516853932584, "no_speech_prob": 0.179056778550148}, {"id": 5, "seek": 0, "start": 28.28, "end": 29.82, "text": " And my mom", "tokens": [51777, 843, 616, 1995, 51854], "temperature": 1.0, "avg_logprob": -3.81935543484158, "compression_ratio": 1.0786516853932584, "no_speech_prob": 0.179056778550148}, {"id": 6, "seek": 2982, "start": 30.54, "end": 33.480000000000004, "text": " And you", "tokens": [50399, 843, 345, 50546], "temperature": 1.0, "avg_logprob": -2.7898615323580227, "compression_ratio": 1.3626373626373627, "no_speech_prob": 0.1458507925271988}, {"id": 7, "seek": 2982, "start": 33.480000000000004, "end": 37.1, "text": " Why the world Hayward", "tokens": [50546, 4162, 262, 995, 41960, 50727], "temperature": 1.0, "avg_logprob": -2.7898615323580227, "compression_ratio": 1.3626373626373627, "no_speech_prob": 0.1458507925271988}, {"id": 8, "seek": 2982, "start": 37.1, "end": 39.16, "text": " And you", "tokens": [50727, 843, 345, 50830], "temperature": 1.0, "avg_logprob": -2.7898615323580227, "compression_ratio": 1.3626373626373627, "no_speech_prob": 0.1458507925271988}, {"id": 9, "seek": 2982, "start": 39.16, "end": 42.56, "text": " And you", "tokens": [50830, 843, 345, 51000], "temperature": 1.0, "avg_logprob": -2.7898615323580227, "compression_ratio": 1.3626373626373627, "no_speech_prob": 0.1458507925271988}, {"id": 10, "seek": 2982, "start": 42.56, "end": 44.88, "text": "att detectives", "tokens": [51000, 1078, 24304, 51116], "temperature": 1.0, "avg_logprob": -2.7898615323580227, "compression_ratio": 1.3626373626373627, "no_speech_prob": 0.1458507925271988}, {"id": 11, "seek": 2982, "start": 44.88, "end": 46.760000000000005, "text": " And you", "tokens": [51116, 843, 345, 51210], "temperature": 1.0, "avg_logprob": -2.7898615323580227, "compression_ratio": 1.3626373626373627, "no_speech_prob": 0.1458507925271988}, {"id": 12, "seek": 2982, "start": 48.120000000000005, "end": 50.400000000000006, "text": " All of you", "tokens": [51278, 1439, 286, 345, 51392], "temperature": 1.0, "avg_logprob": -2.7898615323580227, "compression_ratio": 1.3626373626373627, "no_speech_prob": 0.1458507925271988}, {"id": 13, "seek": 2982, "start": 50.400000000000006, "end": 53.32, "text": " Don't adopted me", "tokens": [51392, 2094, 470, 8197, 502, 51538], "temperature": 1.0, "avg_logprob": -2.7898615323580227, "compression_ratio": 1.3626373626373627, "no_speech_prob": 0.1458507925271988}, {"id": 14, "seek": 2982, "start": 53.32, "end": 54.7, "text": " Even you", "tokens": [51538, 3412, 345, 51607], "temperature": 1.0, "avg_logprob": -2.7898615323580227, "compression_ratio": 1.3626373626373627, "no_speech_prob": 0.1458507925271988}, {"id": 15, "seek": 2982, "start": 54.7, "end": 56.400000000000006, "text": " Only you", "tokens": [51607, 5514, 345, 51692], "temperature": 1.0, "avg_logprob": -2.7898615323580227, "compression_ratio": 1.3626373626373627, "no_speech_prob": 0.1458507925271988}, {"id": 16, "seek": 2982, "start": 56.400000000000006, "end": 57.94, "text": " All of you", "tokens": [51692, 1439, 286, 345, 51769], "temperature": 1.0, "avg_logprob": -2.7898615323580227, "compression_ratio": 1.3626373626373627, "no_speech_prob": 0.1458507925271988}], "language": "en"}